WPEMPhase/CPICANN.py
WPEMPhase/__init__.py
WPEMPhase/data_format.py
WPEMPhase/model.py
WPEMPhase/plot.py
WPEMPhase/config/strucs.csv
WPEMPhase-0.1.1.dist-info/METADATA
WPEMPhase-0.1.1.dist-info/WHEEL
WPEMPhase-0.1.1.dist-info/top_level.txt
WPEMPhase-0.1.1.dist-info/RECORD
